{
    "id": "NCRF",
    "title": "🏦 *National Credit Framework (NCrF)*\n\nFlexible learning & credit mobility 🔄",
    "footer": "Developed by Jit Prajapati",
    "options": {
        "1": {
            "id": "NCRF_OVERVIEW",
            "label": "📘 Overview of NCrF",
            "summary": "NCrF introduces a unified credit system for school, higher education, and vocational education.",
            "detail": "It enables seamless integration between academic and skill-based learning pathways, allowing students to accumulate and transfer credits.",
            "example": "Example: A student earning credits in a vocational course can use them towards a university degree.",
            "pdf_en": "https://www.ugc.gov.in/pdfnews/2609036_Report-of-National-Credit-Framework.pdf",
            "pdf_gu": "GUJARATI_NCRF_LINK"
        },
        "2": {
            "id": "NCRF_LEVELS",
            "label": "📊 Credit Levels (1–8)",
            "summary": "NCrF defines credit levels aligned with learning complexity and progression.",
            "detail": "Levels range from foundational schooling to doctoral-level education, ensuring structured academic growth.",
            "example": "Example: Level 4 may correspond to senior secondary education, while Level 7 corresponds to postgraduate study.",
            "pdf_en": "https://www.ugc.gov.in/pdfnews/2609036_Report-of-National-Credit-Framework.pdf",
            "pdf_gu": "GUJARATI_NCRF_LINK"
        },
        "3": {
            "id": "NCRF_HOURS",
            "label": "⏳ Notional Learning Hours",
            "summary": "Credits are calculated based on notional learning hours.",
            "detail": "One credit typically corresponds to a defined number of learning hours including classroom, practical, and self-study.",
            "example": "Example: 40 hours of learning may equal 1 credit in a structured course.",
            "pdf_en": "https://www.ugc.gov.in/pdfnews/2609036_Report-of-National-Credit-Framework.pdf",
            "pdf_gu": "GUJARATI_NCRF_LINK"
        },
        "4": {
            "id": "NCRF_ABC",
            "label": "🏦 Academic Bank of Credits (ABC)",
            "summary": "ABC digitally stores and tracks academic credits earned by students.",
            "detail": "Students can accumulate credits over time and transfer them across institutions.",
            "example": "Example: A student completing one semester at University A can transfer credits to University B.",
            "pdf_en": "https://www.ugc.gov.in/pdfnews/2609036_Report-of-National-Credit-Framework.pdf",
            "pdf_gu": "GUJARATI_NCRF_LINK"
        },
        "5": {
            "id": "NCRF_RPL",
            "label": "🎖 Recognition of Prior Learning (RPL)",
            "summary": "RPL allows recognition of skills gained through informal or work experience.",
            "detail": "Learners can convert professional experience into academic credits.",
            "example": "Example: A skilled technician can receive academic credits for industry experience.",
            "pdf_en": "https://www.ugc.gov.in/pdfnews/2609036_Report-of-National-Credit-Framework.pdf",
            "pdf_gu": "GUJARATI_NCRF_LINK"
        }
    }
}